anyrunapi/__init__.py
anyrunapi/api.py
anyrunapi/cli.py
anyrunapi-0.1.1.dist-info/entry_points.txt
anyrunapi-0.1.1.dist-info/WHEEL
anyrunapi-0.1.1.dist-info/METADATA
anyrunapi-0.1.1.dist-info/RECORD
