Metadata-Version: 2.1
Name: anyrunapi
Version: 0.1.1
Summary: Library and CLI tool for Any Run (any.run) malware sandbox api.
License: Apache 2.0
Author: Sean McFeely
Author-email: mcfeelynaes@gmail.com
Requires-Python: >=3.6,<4.0
Classifier: License :: Other/Proprietary License
Classifier: Programming Language :: Python :: 3
Classifier: Programming Language :: Python :: 3.6
Classifier: Programming Language :: Python :: 3.7
Classifier: Programming Language :: Python :: 3.8
Classifier: Programming Language :: Python :: 3.9
Requires-Dist: argparse (>=1.4.0,<2.0.0)
Requires-Dist: coloredlogs (>=15.0,<16.0)
Requires-Dist: requests (>=2.25.1,<3.0.0)
